fujin/__init__.py
Fujin-1.0.0.dist-info/METADATA
Fujin-1.0.0.dist-info/WHEEL
Fujin-1.0.0.dist-info/top_level.txt
Fujin-1.0.0.dist-info/RECORD
