Metadata-Version: 2.1
Name: Fujin
Version: 1.0.0
Summary: A Python DoS/DDoS Module
Home-page: https://999root.xyz
Author: 999root (Noire)
Author-email: root@999root.xyz
Project-URL: Docs, https://github.com/999root/Jibaku/tree/main/Fujin
Classifier: Programming Language :: Python :: 3
Classifier: License :: OSI Approved :: MIT License
Classifier: Operating System :: OS Independent
Requires-Python: >=3.6
